AliceGit/Exceptions.py
AliceGit/Git.py
AliceGit/Github.py
AliceGit/__init__.py
AliceGit/pyproject.toml
AliceGit/unittests/__init__.py
AliceGit-1.0.7.dist-info/LICENSE
AliceGit-1.0.7.dist-info/METADATA
AliceGit-1.0.7.dist-info/WHEEL
AliceGit-1.0.7.dist-info/top_level.txt
AliceGit-1.0.7.dist-info/RECORD
