Metadata-Version: 2.1
Name: AliceGit
Version: 1.0.7
Summary: Project Alice Python to Git utilities
Home-page: https://github.com/project-alice-assistant/AliceGit
Author: ProjectAlice
Maintainer: Psychokiller1888
Maintainer-email: laurentchervet@bluewin.ch
License: GPL-3.0
Platform: UNKNOWN
Classifier: Development Status :: 5 - Production/Stable
Classifier: Environment :: Console
Classifier: Intended Audience :: Developers
Classifier: License :: OSI Approved :: GNU General Public License v3 (GPLv3)
Classifier: Operating System :: OS Independent
Classifier: Programming Language :: Python :: 3.9
License-File: LICENSE
Requires-Dist: requests
Requires-Dist: pytest (~=6.2.5)
Requires-Dist: coverage (~=6.3)
Requires-Dist: pytest-cov (~=3.0.0)
Requires-Dist: coveralls (~=3.3.1)
